airbook_mcp_server/__init__.py
airbook_mcp_server-0.0.1.dist-info/METADATA
airbook_mcp_server-0.0.1.dist-info/WHEEL
airbook_mcp_server-0.0.1.dist-info/top_level.txt
airbook_mcp_server-0.0.1.dist-info/RECORD
