Metadata-Version: 2.4
Name: airbook-mcp-server
Version: 0.0.1
Summary: An MCP server for Airbook.
Author-email: priyansh <priyansh@airbook.io>
Project-URL: Homepage, https://github.com/pypa/sampleproject
Project-URL: Bug Tracker, https://github.com/pypa/sampleproject/issues
Classifier: Programming Language :: Python :: 3
Classifier: License :: OSI Approved :: MIT License
Classifier: Operating System :: OS Independent
Requires-Python: >=3.7
Requires-Dist: python-dotenv
Requires-Dist: mcp
